setup.py
Json_And_Xml_Serializer_Eugene.egg-info/PKG-INFO
Json_And_Xml_Serializer_Eugene.egg-info/SOURCES.txt
Json_And_Xml_Serializer_Eugene.egg-info/dependency_links.txt
Json_And_Xml_Serializer_Eugene.egg-info/top_level.txt
serializer/src/__init__.py
serializer/src/constants.py
serializer/src/converter.py
serializer/src/factory.py
serializer/src/json_serializer.py
serializer/src/supportive.py
serializer/src/xml_serializer.py