Metadata-Version: 2.1
Name: Json-And-Xml-Serializer-Eugene
Version: 0.1.0
Summary: Library for class and function serialization
Home-page: UNKNOWN
Author: Evgeny Kuznetsov
Author-email: jenakuz2003@gmail.com
License: UNKNOWN
Platform: UNKNOWN
Classifier: Intended Audience :: Developers
Classifier: Programming Language :: Python :: 3.10
Classifier: Operating System :: OS Independent
